LICENSE
MANIFEST.in
NEWS.rst
README.rst
requirements-test.txt
requirements.txt
setup.py
docs/Makefile
docs/command.rst
docs/conf.py
docs/develop.rst
docs/index.rst
docs/make.bat
docs/news.rst
docs/python.rst
odorik/__init__.py
odorik/config.py
odorik/main.py
odorik/test_main.py
odorik/test_odorik.py
odorik.egg-info/PKG-INFO
odorik.egg-info/SOURCES.txt
odorik.egg-info/dependency_links.txt
odorik.egg-info/entry_points.txt
odorik.egg-info/requires.txt
odorik.egg-info/top_level.txt
odorik/test_data/odorik
odorik/test_data/section