Metadata-Version: 1.1
Name: odorik
Version: 0.5
Summary: Python module for Odorik API.
Home-page: http://cihar.com/software/odorik/
Author: Michal Čihař
Author-email: michal@cihar.com
License: GPLv3+
Download-URL: https://pypi.python.org/pypi/odorik
Keywords: odorik
Platform: any
Classifier: Development Status :: 4 - Beta
Classifier: Topic :: Internet
Classifier: Topic :: Communications :: Telephony
Classifier: Topic :: Software Development :: Libraries :: Python Modules
Classifier: Topic :: Utilities
Classifier: License :: OSI Approved :: GNU General Public License (GPL)
Classifier: Operating System :: OS Independent
Classifier: Intended Audience :: Developers
Classifier: Programming Language :: Python
Classifier: Programming Language :: Python :: 2.7
Classifier: Programming Language :: Python :: 3
Classifier: Programming Language :: Python :: 3.2
Classifier: Programming Language :: Python :: 3.3
Classifier: Programming Language :: Python :: 3.4
